fstrans/__init__.py
fstrans/tests/testfstrans.py
fstrans-1.0.1.dist-info/LICENSE
fstrans-1.0.1.dist-info/METADATA
fstrans-1.0.1.dist-info/WHEEL
fstrans-1.0.1.dist-info/top_level.txt
fstrans-1.0.1.dist-info/RECORD
