Metadata-Version: 2.1
Name: fstrans
Version: 1.0.1
Summary: Performs transactional modification on directory trees
Home-page: https://github.com/vbwagner/fstrans
Author: Victor Wagner
Author-email: vitus@wagner.pp.ru
License: UNKNOWN
Platform: UNKNOWN
Classifier: Programming Language :: Python :: 3
Classifier: License :: OSI Approved :: GNU General Public License v3 (GPLv3)
Classifier: Operating System :: Unix
Classifier: Operating System :: POSIX
Requires-Python: >=3.5
